Metadata-Version: 2.1
Name: Pro-videos-Ferramentas-teste
Version: 1.0
Summary: Este pacote de teste, ferramentas de processamento de video
Author: Uilson Cruz
Author-email: uilsoncruz1996@gmal.com
Keywords: Camera,Video,Processamento
License-File: license.txt
